aibro/__init__.py
aibro/comm.py
aibro/constant.py
aibro/inference.py
aibro/job.py
aibro/training.py
aibro/scripts/__init__.py
aibro/scripts/call_predict.sh
aibro/scripts/infer_command.sh
aibro/scripts/win_call_predict.bat
aibro/scripts/win_infer_command.bat
aibro/tools/__init__.py
aibro/tools/auth.py
aibro/tools/marketplace.py
aibro/tools/online_pickup.py
aibro/tools/prints.py
aibro/tools/spot.py
aibro/tools/utils.py
aibro/tools/utils_training.py
aibro/tools/helpers/__init__.py
aibro/tools/helpers/input_assertions.py
aibro/tools/service/__init__.py
aibro/tools/service/api_service.py
aibro/tools/sio/__init__.py
aibro/tools/sio/sio.py
aibro/tools/sio/sio_follow.py
aibro/tools/sio/sio_follow_inf.py
aibro/tools/sio/sio_spot.py
aibro-1.1.5.data/scripts/call_predict.sh
aibro-1.1.5.data/scripts/infer_command.sh
aibro-1.1.5.data/scripts/win_call_predict.bat
aibro-1.1.5.data/scripts/win_infer_command.bat
aibro-1.1.5.dist-info/METADATA
aibro-1.1.5.dist-info/WHEEL
aibro-1.1.5.dist-info/top_level.txt
aibro-1.1.5.dist-info/RECORD
