Metadata-Version: 2.1
Name: aibro
Version: 1.1.5
Summary: Serverless model training
Home-page: https://github.com/AIpaca-Inc/AIbro_lib
Author: AIpaca.ai
Author-email: hello@aipaca.ai
License: UNKNOWN
Project-URL: Bug Tracker, https://github.com/AIpaca-Inc/AIbro_lib/issues
Platform: UNKNOWN
Classifier: Programming Language :: Python :: 3
Classifier: License :: OSI Approved :: MIT License
Classifier: Operating System :: OS Independent
Requires-Python: >=3.6
Requires-Dist: appdirs (==1.4.4)
Requires-Dist: args (==0.1.0)
Requires-Dist: attrs (==21.2.0)
Requires-Dist: bidict (==0.21.2)
Requires-Dist: bleach (==3.3.0)
Requires-Dist: build (==0.3.1.post1)
Requires-Dist: certifi (==2020.12.5)
Requires-Dist: cfgv (==3.2.0)
Requires-Dist: chardet (==4.0.0)
Requires-Dist: clint (==0.5.1)
Requires-Dist: colorama (==0.4.4)
Requires-Dist: distlib (==0.3.1)
Requires-Dist: dnspython (==2.1.0)
Requires-Dist: docutils (==0.17.1)
Requires-Dist: eventlet (==0.32.0)
Requires-Dist: filelock (==3.0.12)
Requires-Dist: greenlet (==1.1.1)
Requires-Dist: identify (==2.2.4)
Requires-Dist: idna (==2.10)
Requires-Dist: importlib-metadata (==4.0.1)
Requires-Dist: iniconfig (==1.1.1)
Requires-Dist: keyring (==23.0.1)
Requires-Dist: nodeenv (==1.6.0)
Requires-Dist: numpy (==1.19.5)
Requires-Dist: objsize (==0.3.3)
Requires-Dist: packaging (==20.9)
Requires-Dist: pandas (==1.2.5)
Requires-Dist: pep517 (==0.10.0)
Requires-Dist: pkginfo (==1.7.0)
Requires-Dist: plotly (==5.1.0)
Requires-Dist: pluggy (==0.13.1)
Requires-Dist: pre-commit (==2.12.1)
Requires-Dist: py (==1.10.0)
Requires-Dist: pygments (==2.9.0)
Requires-Dist: pyparsing (==2.4.7)
Requires-Dist: pytest (==6.2.4)
Requires-Dist: pytest-mock (==3.6.1)
Requires-Dist: python-dateutil (==2.8.1)
Requires-Dist: python-dotenv (==0.17.1)
Requires-Dist: python-engineio (==4.1.0)
Requires-Dist: python-socketio[client] (==5.2.1)
Requires-Dist: pytz (==2021.1)
Requires-Dist: pyyaml (==5.4.1)
Requires-Dist: readme-renderer (==29.0)
Requires-Dist: requests (==2.25.1)
Requires-Dist: requests-toolbelt (==0.9.1)
Requires-Dist: rfc3986 (==1.4.0)
Requires-Dist: six (==1.15.0)
Requires-Dist: tenacity (==7.0.0)
Requires-Dist: toml (==0.10.2)
Requires-Dist: tqdm (==4.60.0)
Requires-Dist: twine (==3.4.1)
Requires-Dist: typing-extensions (==3.7.4.3)
Requires-Dist: urllib3 (==1.26.4)
Requires-Dist: virtualenv (==20.4.6)
Requires-Dist: webencodings (==0.5.1)
Requires-Dist: websocket-client (==0.58.0)
Requires-Dist: zipp (==3.4.1)
